setup.py
gaubi/Binomialdistribution.py
gaubi/Gaussiandistribution.py
gaubi/Generaldistribution.py
gaubi/__init__.py
gaubi/example_code.py
gaubi.egg-info/PKG-INFO
gaubi.egg-info/SOURCES.txt
gaubi.egg-info/dependency_links.txt
gaubi.egg-info/not-zip-safe
gaubi.egg-info/top_level.txt