Metadata-Version: 1.0
Name: gaubi
Version: 1.0
Summary: Gaussian and Binomial distributions
Home-page: UNKNOWN
Author: Gabriel Estivalet
Author-email: gestivalet@gmail.com
License: UNKNOWN
Platform: UNKNOWN
